vtrust/__init__.py
vtrust/check_security_headers.py
vtrust/check_ssl.py
vtrust/vtrust.py
vtrust/whois_checker.py
vtrust-0.1.3.dist-info/LICENSE
vtrust-0.1.3.dist-info/METADATA
vtrust-0.1.3.dist-info/WHEEL
vtrust-0.1.3.dist-info/RECORD
