Metadata-Version: 2.3
Name: vtrust
Version: 0.1.3
Summary: VTrust is a Python library that helps check website security.
License: GPL-3.0
Keywords: whois,cybersecurity,python,vtrust
Author: Victor
Author-email: hugovictor.dev@gmail.com
Requires-Python: >=3.13,<4.0
Classifier: License :: OSI Approved :: GNU General Public License v3 (GPLv3)
Classifier: Programming Language :: Python :: 3
Classifier: Programming Language :: Python :: 3.13
Requires-Dist: colorama (>=0.4.6,<0.5.0)
Requires-Dist: httpx (>=0.28.1,<0.29.0)
Requires-Dist: python-whois (>=0.9.5,<0.10.0)
